automation_text_detection/__init__.py
automation_text_detection/automation_text_detection.py
automation_text_detection-0.1.0.dist-info/licenses/LICENSE
automation_text_detection-0.1.0.dist-info/METADATA
automation_text_detection-0.1.0.dist-info/WHEEL
automation_text_detection-0.1.0.dist-info/entry_points.txt
automation_text_detection-0.1.0.dist-info/top_level.txt
automation_text_detection-0.1.0.dist-info/RECORD
