Metadata-Version: 2.4
Name: automation_text_detection
Version: 0.1.0
Summary: OCR text matching tool using EasyOCR
Author: Shivam Koshta
Author-email: skoshta@nvidia.com
Requires-Python: >=3.7
License-File: LICENSE
Requires-Dist: easyocr
Requires-Dist: numpy
Requires-Dist: tqdm
Dynamic: author
Dynamic: author-email
Dynamic: license-file
Dynamic: requires-dist
Dynamic: requires-python
Dynamic: summary
